[
  {
    "id": 1,
    "date": "Oct 19",
    "activity": "Orientation + Tablecloth Activity / Walking Intro",
    "type": "regular"
  },
  {
    "id": 2,
    "date": "Oct 26",
    "activity": "Public Speaking Workshop: Self-Reflection and On-Stage Bio",
    "type": "regular"
  },
  {
    "id": 3,
    "date": "Nov 2",
    "activity": "Walking Workshop: How to Pageant Walk",
    "type": "regular"
  },
  {
    "id": 4,
    "date": "Nov 9",
    "activity": "Platform Building: Vision Board",
    "type": "regular"
  },
  {
    "id": 5,
    "date": "Nov 16",
    "activity": "Interview Practice",
    "type": "regular"
  },
  {
    "id": 6,
    "date": "Nov 23",
    "activity": "Ao Dai Headshots + Thanksgiving Potluck",
    "type": "regular"
  },
  {
    "id": 7,
    "date": "Nov 30",
    "activity": "NO PRACTICE",
    "type": "no-practice"
  },
  {
    "id": 8,
    "date": "Dec 7",
    "activity": "Service Workshop",
    "type": "regular"
  },
  {
    "id": 9,
    "date": "Dec 14",
    "activity": "Outdoor Photoshoot",
    "type": "regular"
  },
  {
    "id": 10,
    "date": "Dec 21",
    "activity": "NO PRACTICE",
    "type": "no-practice"
  },
  {
    "id": 11,
    "date": "Dec 28",
    "activity": "NO PRACTICE",
    "type": "no-practice"
  },
  {
    "id": 12,
    "date": "Jan 4",
    "activity": "Dance only",
    "type": "regular"
  },
  {
    "id": 13,
    "date": "Jan 11",
    "activity": "Public Speaking Workshop: Vietnamese Language and Culture + On Stage Q&A",
    "type": "regular"
  },
  {
    "id": 14,
    "date": "Jan 18",
    "activity": "Walking",
    "type": "regular"
  },
  {
    "id": 15,
    "date": "Jan 25",
    "activity": "Interview Workshop",
    "type": "regular"
  },
  {
    "id": 16,
    "date": "Feb 1",
    "activity": "Vietnamese Identity + Q&A",
    "type": "regular"
  },
  {
    "id": 17,
    "date": "Feb 8",
    "activity": "Crowning + Transitions",
    "type": "regular"
  },
  {
    "id": 18,
    "date": "Feb 15",
    "activity": "NO PRACTICE",
    "type": "no-practice"
  },
  {
    "id": 19,
    "date": "Feb 19",
    "activity": "Stage rehearsal",
    "type": "regular"
  },
  {
    "id": 20,
    "date": "Feb 20",
    "activity": "Alumni fashion show",
    "type": "regular"
  },
  {
    "id": 21,
    "date": "Feb 21",
    "activity": "Pageant Day",
    "type": "regular"
  }
]
